{
  "ExchangeID": "SZ",
  "InstrumentID": "000159",
  "InstrumentName": "国际实业",
  "ProductID": "",
  "ProductName": "",
  "ProductType": null,
  "ExchangeCode": "000159",
  "UniCode": "000159",
  "CreateDate": "0",
  "OpenDate": "20000926",
  "ExpireDate": "99999999",
  "PreClose": 5.86,
  "SettlementPrice": 5.86,
  "UpStopPrice": 6.45,
  "DownStopPrice": 5.2700000000000005,
  "FloatVolume": 480672868.0,
  "TotalVolume": 480685993.0,
  "LongMarginRatio": 0.0,
  "ShortMarginRatio": 0.0,
  "PriceTick": 0.01,
  "VolumeMultiple": 1,
  "MainContract": 0,
  "LastVolume": 0,
  "InstrumentStatus": 0,
  "IsTrading": false,
  "IsRecent": false,
  "ProductTradeQuota": 0,
  "ContractTradeQuota": 0,
  "ProductOpenInterestQuota": 0,
  "ContractOpenInterestQuota": 0
}