{
  "ExchangeID": "SZ",
  "InstrumentID": "000525",
  "InstrumentName": "红太阳",
  "ProductID": "",
  "ProductName": "",
  "ProductType": null,
  "ExchangeCode": "000525",
  "UniCode": "000525",
  "CreateDate": "0",
  "OpenDate": "19931028",
  "ExpireDate": "99999999",
  "PreClose": 7.44,
  "SettlementPrice": 7.44,
  "UpStopPrice": 8.18,
  "DownStopPrice": 6.7,
  "FloatVolume": 990077577.0,
  "TotalVolume": 1298027341.0,
  "LongMarginRatio": 0.0,
  "ShortMarginRatio": 0.0,
  "PriceTick": 0.01,
  "VolumeMultiple": 1,
  "MainContract": 0,
  "LastVolume": 0,
  "InstrumentStatus": 0,
  "IsTrading": false,
  "IsRecent": false,
  "ProductTradeQuota": 0,
  "ContractTradeQuota": 0,
  "ProductOpenInterestQuota": 0,
  "ContractOpenInterestQuota": 0
}