{
  "ExchangeID": "SZ",
  "InstrumentID": "000756",
  "InstrumentName": "新华制药",
  "ProductID": "",
  "ProductName": "",
  "ProductType": null,
  "ExchangeCode": "000756",
  "UniCode": "000756",
  "CreateDate": "0",
  "OpenDate": "19970806",
  "ExpireDate": "99999999",
  "PreClose": 17.1,
  "SettlementPrice": 17.1,
  "UpStopPrice": 18.81,
  "DownStopPrice": 15.39,
  "FloatVolume": 492623924.0,
  "TotalVolume": 494776535.0,
  "LongMarginRatio": 0.0,
  "ShortMarginRatio": 0.0,
  "PriceTick": 0.01,
  "VolumeMultiple": 1,
  "MainContract": 0,
  "LastVolume": 0,
  "InstrumentStatus": 0,
  "IsTrading": false,
  "IsRecent": false,
  "ProductTradeQuota": 0,
  "ContractTradeQuota": 0,
  "ProductOpenInterestQuota": 0,
  "ContractOpenInterestQuota": 0
}