{
  "ExchangeID": "SZ",
  "InstrumentID": "002053",
  "InstrumentName": "云南能投",
  "ProductID": "",
  "ProductName": "",
  "ProductType": null,
  "ExchangeCode": "002053",
  "UniCode": "002053",
  "CreateDate": "0",
  "OpenDate": "20060627",
  "ExpireDate": "99999999",
  "PreClose": 10.98,
  "SettlementPrice": 10.98,
  "UpStopPrice": 12.08,
  "DownStopPrice": 9.88,
  "FloatVolume": 920700299.0,
  "TotalVolume": 920729464.0,
  "LongMarginRatio": 0.0,
  "ShortMarginRatio": 0.0,
  "PriceTick": 0.01,
  "VolumeMultiple": 1,
  "MainContract": 0,
  "LastVolume": 0,
  "InstrumentStatus": 0,
  "IsTrading": false,
  "IsRecent": false,
  "ProductTradeQuota": 0,
  "ContractTradeQuota": 0,
  "ProductOpenInterestQuota": 0,
  "ContractOpenInterestQuota": 0
}