{
  "ExchangeID": "SZ",
  "InstrumentID": "002001",
  "InstrumentName": "新 和 成",
  "ProductID": "",
  "ProductName": "",
  "ProductType": null,
  "ExchangeCode": "002001",
  "UniCode": "002001",
  "CreateDate": "0",
  "OpenDate": "20040625",
  "ExpireDate": "99999999",
  "PreClose": 22.48,
  "SettlementPrice": 22.48,
  "UpStopPrice": 24.73,
  "DownStopPrice": 20.23,
  "FloatVolume": 3037011928.0,
  "TotalVolume": 3073421680.0,
  "LongMarginRatio": 0.0,
  "ShortMarginRatio": 0.0,
  "PriceTick": 0.01,
  "VolumeMultiple": 1,
  "MainContract": 0,
  "LastVolume": 0,
  "InstrumentStatus": 0,
  "IsTrading": false,
  "IsRecent": false,
  "ProductTradeQuota": 0,
  "ContractTradeQuota": 0,
  "ProductOpenInterestQuota": 0,
  "ContractOpenInterestQuota": 0
}