{
  "ExchangeID": "SZ",
  "InstrumentID": "002019",
  "InstrumentName": "亿帆医药",
  "ProductID": "",
  "ProductName": "",
  "ProductType": null,
  "ExchangeCode": "002019",
  "UniCode": "002019",
  "CreateDate": "0",
  "OpenDate": "20040713",
  "ExpireDate": "99999999",
  "PreClose": 13.9,
  "SettlementPrice": 13.9,
  "UpStopPrice": 15.290000000000001,
  "DownStopPrice": 12.51,
  "FloatVolume": 841474080.0,
  "TotalVolume": 1216390085.0,
  "LongMarginRatio": 0.0,
  "ShortMarginRatio": 0.0,
  "PriceTick": 0.01,
  "VolumeMultiple": 1,
  "MainContract": 0,
  "LastVolume": 0,
  "InstrumentStatus": 0,
  "IsTrading": false,
  "IsRecent": false,
  "ProductTradeQuota": 0,
  "ContractTradeQuota": 0,
  "ProductOpenInterestQuota": 0,
  "ContractOpenInterestQuota": 0
}