{
  "ExchangeID": "SZ",
  "InstrumentID": "002021",
  "InstrumentName": "中捷资源",
  "ProductID": "",
  "ProductName": "",
  "ProductType": null,
  "ExchangeCode": "002021",
  "UniCode": "002021",
  "CreateDate": "0",
  "OpenDate": "20040715",
  "ExpireDate": "99999999",
  "PreClose": 2.41,
  "SettlementPrice": 2.41,
  "UpStopPrice": 2.65,
  "DownStopPrice": 2.17,
  "FloatVolume": 1195437891.0,
  "TotalVolume": 1195477323.0,
  "LongMarginRatio": 0.0,
  "ShortMarginRatio": 0.0,
  "PriceTick": 0.01,
  "VolumeMultiple": 1,
  "MainContract": 0,
  "LastVolume": 0,
  "InstrumentStatus": 0,
  "IsTrading": false,
  "IsRecent": false,
  "ProductTradeQuota": 0,
  "ContractTradeQuota": 0,
  "ProductOpenInterestQuota": 0,
  "ContractOpenInterestQuota": 0
}