{
  "ExchangeID": "SZ",
  "InstrumentID": "002164",
  "InstrumentName": "宁波东力",
  "ProductID": "",
  "ProductName": "",
  "ProductType": null,
  "ExchangeCode": "002164",
  "UniCode": "002164",
  "CreateDate": "0",
  "OpenDate": "20070823",
  "ExpireDate": "99999999",
  "PreClose": 9.25,
  "SettlementPrice": 9.25,
  "UpStopPrice": 10.18,
  "DownStopPrice": 8.33,
  "FloatVolume": 479775218.0,
  "TotalVolume": 532173689.0,
  "LongMarginRatio": 0.0,
  "ShortMarginRatio": 0.0,
  "PriceTick": 0.01,
  "VolumeMultiple": 1,
  "MainContract": 0,
  "LastVolume": 0,
  "InstrumentStatus": 0,
  "IsTrading": false,
  "IsRecent": false,
  "ProductTradeQuota": 0,
  "ContractTradeQuota": 0,
  "ProductOpenInterestQuota": 0,
  "ContractOpenInterestQuota": 0
}