{
  "ExchangeID": "SZ",
  "InstrumentID": "002330",
  "InstrumentName": "得利斯",
  "ProductID": "",
  "ProductName": "",
  "ProductType": null,
  "ExchangeCode": "002330",
  "UniCode": "002330",
  "CreateDate": "0",
  "OpenDate": "20100106",
  "ExpireDate": "99999999",
  "PreClose": 4.83,
  "SettlementPrice": 4.83,
  "UpStopPrice": 5.3100000000000005,
  "DownStopPrice": 4.3500000000000005,
  "FloatVolume": 635178715.0,
  "TotalVolume": 635315290.0,
  "LongMarginRatio": 0.0,
  "ShortMarginRatio": 0.0,
  "PriceTick": 0.01,
  "VolumeMultiple": 1,
  "MainContract": 0,
  "LastVolume": 0,
  "InstrumentStatus": 0,
  "IsTrading": false,
  "IsRecent": false,
  "ProductTradeQuota": 0,
  "ContractTradeQuota": 0,
  "ProductOpenInterestQuota": 0,
  "ContractOpenInterestQuota": 0
}