{
  "ExchangeID": "SZ",
  "InstrumentID": "002470",
  "InstrumentName": "金正大",
  "ProductID": "",
  "ProductName": "",
  "ProductType": null,
  "ExchangeCode": "002470",
  "UniCode": "002470",
  "CreateDate": "0",
  "OpenDate": "20100908",
  "ExpireDate": "99999999",
  "PreClose": 1.79,
  "SettlementPrice": 1.79,
  "UpStopPrice": 1.97,
  "DownStopPrice": 1.61,
  "FloatVolume": 3285749417.0,
  "TotalVolume": 3286027742.0,
  "LongMarginRatio": 0.0,
  "ShortMarginRatio": 0.0,
  "PriceTick": 0.01,
  "VolumeMultiple": 1,
  "MainContract": 0,
  "LastVolume": 0,
  "InstrumentStatus": 0,
  "IsTrading": false,
  "IsRecent": false,
  "ProductTradeQuota": 0,
  "ContractTradeQuota": 0,
  "ProductOpenInterestQuota": 0,
  "ContractOpenInterestQuota": 0
}