{
  "ExchangeID": "SZ",
  "InstrumentID": "002522",
  "InstrumentName": "浙江众成",
  "ProductID": "",
  "ProductName": "",
  "ProductType": null,
  "ExchangeCode": "002522",
  "UniCode": "002522",
  "CreateDate": "0",
  "OpenDate": "20101210",
  "ExpireDate": "99999999",
  "PreClose": 5.12,
  "SettlementPrice": 5.12,
  "UpStopPrice": 5.63,
  "DownStopPrice": 4.61,
  "FloatVolume": 905019879.0,
  "TotalVolume": 905779387.0,
  "LongMarginRatio": 0.0,
  "ShortMarginRatio": 0.0,
  "PriceTick": 0.01,
  "VolumeMultiple": 1,
  "MainContract": 0,
  "LastVolume": 0,
  "InstrumentStatus": 0,
  "IsTrading": false,
  "IsRecent": false,
  "ProductTradeQuota": 0,
  "ContractTradeQuota": 0,
  "ProductOpenInterestQuota": 0,
  "ContractOpenInterestQuota": 0
}