{
  "ExchangeID": "SZ",
  "InstrumentID": "002535",
  "InstrumentName": "林州重机",
  "ProductID": "",
  "ProductName": "",
  "ProductType": null,
  "ExchangeCode": "002535",
  "UniCode": "002535",
  "CreateDate": "0",
  "OpenDate": "20110111",
  "ExpireDate": "99999999",
  "PreClose": 4.19,
  "SettlementPrice": 4.19,
  "UpStopPrice": 4.61,
  "DownStopPrice": 3.77,
  "FloatVolume": 746338485.0,
  "TotalVolume": 801683074.0,
  "LongMarginRatio": 0.0,
  "ShortMarginRatio": 0.0,
  "PriceTick": 0.01,
  "VolumeMultiple": 1,
  "MainContract": 0,
  "LastVolume": 0,
  "InstrumentStatus": 0,
  "IsTrading": false,
  "IsRecent": false,
  "ProductTradeQuota": 0,
  "ContractTradeQuota": 0,
  "ProductOpenInterestQuota": 0,
  "ContractOpenInterestQuota": 0
}