{
  "ExchangeID": "SZ",
  "InstrumentID": "002692",
  "InstrumentName": "远程股份",
  "ProductID": "",
  "ProductName": "",
  "ProductType": null,
  "ExchangeCode": "002692",
  "UniCode": "002692",
  "CreateDate": "0",
  "OpenDate": "20120808",
  "ExpireDate": "99999999",
  "PreClose": 5.08,
  "SettlementPrice": 5.08,
  "UpStopPrice": 5.59,
  "DownStopPrice": 4.57,
  "FloatVolume": 717864975.0,
  "TotalVolume": 718146000.0,
  "LongMarginRatio": 0.0,
  "ShortMarginRatio": 0.0,
  "PriceTick": 0.01,
  "VolumeMultiple": 1,
  "MainContract": 0,
  "LastVolume": 0,
  "InstrumentStatus": 0,
  "IsTrading": false,
  "IsRecent": false,
  "ProductTradeQuota": 0,
  "ContractTradeQuota": 0,
  "ProductOpenInterestQuota": 0,
  "ContractOpenInterestQuota": 0
}