{
  "ExchangeID": "SZ",
  "InstrumentID": "002780",
  "InstrumentName": "三夫户外",
  "ProductID": "",
  "ProductName": "",
  "ProductType": null,
  "ExchangeCode": "002780",
  "UniCode": "002780",
  "CreateDate": "0",
  "OpenDate": "20151209",
  "ExpireDate": "99999999",
  "PreClose": 14.04,
  "SettlementPrice": 14.04,
  "UpStopPrice": 15.44,
  "DownStopPrice": 12.64,
  "FloatVolume": 130652734.0,
  "TotalVolume": 157587486.0,
  "LongMarginRatio": 0.0,
  "ShortMarginRatio": 0.0,
  "PriceTick": 0.01,
  "VolumeMultiple": 1,
  "MainContract": 0,
  "LastVolume": 0,
  "InstrumentStatus": 0,
  "IsTrading": false,
  "IsRecent": false,
  "ProductTradeQuota": 0,
  "ContractTradeQuota": 0,
  "ProductOpenInterestQuota": 0,
  "ContractOpenInterestQuota": 0
}