{
  "ExchangeID": "SZ",
  "InstrumentID": "002881",
  "InstrumentName": "美格智能",
  "ProductID": "",
  "ProductName": "",
  "ProductType": null,
  "ExchangeCode": "002881",
  "UniCode": "002881",
  "CreateDate": "0",
  "OpenDate": "20170622",
  "ExpireDate": "99999999",
  "PreClose": 45.6,
  "SettlementPrice": 45.6,
  "UpStopPrice": 50.160000000000004,
  "DownStopPrice": 41.04,
  "FloatVolume": 181048114.0,
  "TotalVolume": 261801844.0,
  "LongMarginRatio": 0.0,
  "ShortMarginRatio": 0.0,
  "PriceTick": 0.01,
  "VolumeMultiple": 1,
  "MainContract": 0,
  "LastVolume": 0,
  "InstrumentStatus": 0,
  "IsTrading": false,
  "IsRecent": false,
  "ProductTradeQuota": 0,
  "ContractTradeQuota": 0,
  "ProductOpenInterestQuota": 0,
  "ContractOpenInterestQuota": 0
}