{
  "ExchangeID": "SZ",
  "InstrumentID": "002851",
  "InstrumentName": "麦格米特",
  "ProductID": "",
  "ProductName": "",
  "ProductType": null,
  "ExchangeCode": "002851",
  "UniCode": "002851",
  "CreateDate": "0",
  "OpenDate": "20170306",
  "ExpireDate": "99999999",
  "PreClose": 53.79,
  "SettlementPrice": 53.79,
  "UpStopPrice": 59.17,
  "DownStopPrice": 48.410000000000004,
  "FloatVolume": 455465114.0,
  "TotalVolume": 547693154.0,
  "LongMarginRatio": 0.0,
  "ShortMarginRatio": 0.0,
  "PriceTick": 0.01,
  "VolumeMultiple": 1,
  "MainContract": 0,
  "LastVolume": 0,
  "InstrumentStatus": 0,
  "IsTrading": false,
  "IsRecent": false,
  "ProductTradeQuota": 0,
  "ContractTradeQuota": 0,
  "ProductOpenInterestQuota": 0,
  "ContractOpenInterestQuota": 0
}