{
  "ExchangeID": "SZ",
  "InstrumentID": "002886",
  "InstrumentName": "沃特股份",
  "ProductID": "",
  "ProductName": "",
  "ProductType": null,
  "ExchangeCode": "002886",
  "UniCode": "002886",
  "CreateDate": "0",
  "OpenDate": "20170627",
  "ExpireDate": "99999999",
  "PreClose": 19.22,
  "SettlementPrice": 19.22,
  "UpStopPrice": 21.14,
  "DownStopPrice": 17.3,
  "FloatVolume": 209078164.0,
  "TotalVolume": 263203565.0,
  "LongMarginRatio": 0.0,
  "ShortMarginRatio": 0.0,
  "PriceTick": 0.01,
  "VolumeMultiple": 1,
  "MainContract": 0,
  "LastVolume": 0,
  "InstrumentStatus": 0,
  "IsTrading": false,
  "IsRecent": false,
  "ProductTradeQuota": 0,
  "ContractTradeQuota": 0,
  "ProductOpenInterestQuota": 0,
  "ContractOpenInterestQuota": 0
}