{
  "ExchangeID": "SZ",
  "InstrumentID": "002975",
  "InstrumentName": "博杰股份",
  "ProductID": "",
  "ProductName": "",
  "ProductType": null,
  "ExchangeCode": "002975",
  "UniCode": "002975",
  "CreateDate": "0",
  "OpenDate": "20200205",
  "ExpireDate": "99999999",
  "PreClose": 38.18,
  "SettlementPrice": 38.18,
  "UpStopPrice": 42.0,
  "DownStopPrice": 34.36,
  "FloatVolume": 105858980.0,
  "TotalVolume": 158502693.0,
  "LongMarginRatio": 0.0,
  "ShortMarginRatio": 0.0,
  "PriceTick": 0.01,
  "VolumeMultiple": 1,
  "MainContract": 0,
  "LastVolume": 0,
  "InstrumentStatus": 0,
  "IsTrading": false,
  "IsRecent": false,
  "ProductTradeQuota": 0,
  "ContractTradeQuota": 0,
  "ProductOpenInterestQuota": 0,
  "ContractOpenInterestQuota": 0
}