{
  "ExchangeID": "SZ",
  "InstrumentID": "002955",
  "InstrumentName": "鸿合科技",
  "ProductID": "",
  "ProductName": "",
  "ProductType": null,
  "ExchangeCode": "002955",
  "UniCode": "002955",
  "CreateDate": "0",
  "OpenDate": "20190523",
  "ExpireDate": "99999999",
  "PreClose": 25.27,
  "SettlementPrice": 25.27,
  "UpStopPrice": 27.8,
  "DownStopPrice": 22.740000000000002,
  "FloatVolume": 187377720.0,
  "TotalVolume": 236639912.0,
  "LongMarginRatio": 0.0,
  "ShortMarginRatio": 0.0,
  "PriceTick": 0.01,
  "VolumeMultiple": 1,
  "MainContract": 0,
  "LastVolume": 0,
  "InstrumentStatus": 0,
  "IsTrading": false,
  "IsRecent": false,
  "ProductTradeQuota": 0,
  "ContractTradeQuota": 0,
  "ProductOpenInterestQuota": 0,
  "ContractOpenInterestQuota": 0
}