{
  "ExchangeID": "SZ",
  "InstrumentID": "002961",
  "InstrumentName": "瑞达期货",
  "ProductID": "",
  "ProductName": "",
  "ProductType": null,
  "ExchangeCode": "002961",
  "UniCode": "002961",
  "CreateDate": "0",
  "OpenDate": "20190905",
  "ExpireDate": "99999999",
  "PreClose": 22.34,
  "SettlementPrice": 22.34,
  "UpStopPrice": 24.57,
  "DownStopPrice": 20.11,
  "FloatVolume": 445033512.0,
  "TotalVolume": 445035762.0,
  "LongMarginRatio": 0.0,
  "ShortMarginRatio": 0.0,
  "PriceTick": 0.01,
  "VolumeMultiple": 1,
  "MainContract": 0,
  "LastVolume": 0,
  "InstrumentStatus": 0,
  "IsTrading": false,
  "IsRecent": false,
  "ProductTradeQuota": 0,
  "ContractTradeQuota": 0,
  "ProductOpenInterestQuota": 0,
  "ContractOpenInterestQuota": 0
}