{
  "ExchangeID": "SZ",
  "InstrumentID": "159398",
  "InstrumentName": "信用债ETF天弘",
  "ProductID": "",
  "ProductName": "",
  "ProductType": null,
  "ExchangeCode": "159398",
  "UniCode": "159398",
  "CreateDate": "0",
  "OpenDate": "20250206",
  "ExpireDate": "99999999",
  "PreClose": 100.701,
  "SettlementPrice": 100.701,
  "UpStopPrice": 110.771,
  "DownStopPrice": 90.631,
  "FloatVolume": 109002310.0,
  "TotalVolume": 115682310.0,
  "LongMarginRatio": 0.0,
  "ShortMarginRatio": 0.0,
  "PriceTick": 0.001,
  "VolumeMultiple": 1,
  "MainContract": 0,
  "LastVolume": 0,
  "InstrumentStatus": 0,
  "IsTrading": false,
  "IsRecent": false,
  "ProductTradeQuota": 0,
  "ContractTradeQuota": 0,
  "ProductOpenInterestQuota": 0,
  "ContractOpenInterestQuota": 0
}