{
  "ExchangeID": "SZ",
  "InstrumentID": "159351",
  "InstrumentName": "A500ETF嘉实",
  "ProductID": "",
  "ProductName": "",
  "ProductType": null,
  "ExchangeCode": "159351",
  "UniCode": "159351",
  "CreateDate": "0",
  "OpenDate": "20241015",
  "ExpireDate": "99999999",
  "PreClose": 1.041,
  "SettlementPrice": 1.041,
  "UpStopPrice": 1.145,
  "DownStopPrice": 0.937,
  "FloatVolume": 12560123357.0,
  "TotalVolume": 17951123357.0,
  "LongMarginRatio": 0.0,
  "ShortMarginRatio": 0.0,
  "PriceTick": 0.001,
  "VolumeMultiple": 1,
  "MainContract": 0,
  "LastVolume": 0,
  "InstrumentStatus": 0,
  "IsTrading": false,
  "IsRecent": false,
  "ProductTradeQuota": 0,
  "ContractTradeQuota": 0,
  "ProductOpenInterestQuota": 0,
  "ContractOpenInterestQuota": 0
}