{
  "ExchangeID": "SZ",
  "InstrumentID": "159368",
  "InstrumentName": "创业板新能源ETF华夏",
  "ProductID": "",
  "ProductName": "",
  "ProductType": null,
  "ExchangeCode": "159368",
  "UniCode": "159368",
  "CreateDate": "0",
  "OpenDate": "20250324",
  "ExpireDate": "99999999",
  "PreClose": 1.005,
  "SettlementPrice": 1.005,
  "UpStopPrice": 1.206,
  "DownStopPrice": 0.804,
  "FloatVolume": 70289841.0,
  "TotalVolume": 108289841.0,
  "LongMarginRatio": 0.0,
  "ShortMarginRatio": 0.0,
  "PriceTick": 0.001,
  "VolumeMultiple": 1,
  "MainContract": 0,
  "LastVolume": 0,
  "InstrumentStatus": 0,
  "IsTrading": false,
  "IsRecent": false,
  "ProductTradeQuota": 0,
  "ContractTradeQuota": 0,
  "ProductOpenInterestQuota": 0,
  "ContractOpenInterestQuota": 0
}