{
  "ExchangeID": "SZ",
  "InstrumentID": "159619",
  "InstrumentName": "基建ETF",
  "ProductID": "",
  "ProductName": "",
  "ProductType": null,
  "ExchangeCode": "159619",
  "UniCode": "159619",
  "CreateDate": "0",
  "OpenDate": "20220218",
  "ExpireDate": "99999999",
  "PreClose": 1.04,
  "SettlementPrice": 1.04,
  "UpStopPrice": 1.1440000000000001,
  "DownStopPrice": 0.936,
  "FloatVolume": 339981007.0,
  "TotalVolume": 339981007.0,
  "LongMarginRatio": 0.0,
  "ShortMarginRatio": 0.0,
  "PriceTick": 0.001,
  "VolumeMultiple": 1,
  "MainContract": 0,
  "LastVolume": 0,
  "InstrumentStatus": 0,
  "IsTrading": false,
  "IsRecent": false,
  "ProductTradeQuota": 0,
  "ContractTradeQuota": 0,
  "ProductOpenInterestQuota": 0,
  "ContractOpenInterestQuota": 0
}