{
  "ExchangeID": "SZ",
  "InstrumentID": "159791",
  "InstrumentName": "300ESGETF",
  "ProductID": "",
  "ProductName": "",
  "ProductType": null,
  "ExchangeCode": "159791",
  "UniCode": "159791",
  "CreateDate": "0",
  "OpenDate": "20220308",
  "ExpireDate": "99999999",
  "PreClose": 0.989,
  "SettlementPrice": 0.989,
  "UpStopPrice": 1.088,
  "DownStopPrice": 0.89,
  "FloatVolume": 33083347.0,
  "TotalVolume": 33083347.0,
  "LongMarginRatio": 0.0,
  "ShortMarginRatio": 0.0,
  "PriceTick": 0.001,
  "VolumeMultiple": 1,
  "MainContract": 0,
  "LastVolume": 0,
  "InstrumentStatus": 0,
  "IsTrading": false,
  "IsRecent": false,
  "ProductTradeQuota": 0,
  "ContractTradeQuota": 0,
  "ProductOpenInterestQuota": 0,
  "ContractOpenInterestQuota": 0
}