{
  "ExchangeID": "SZ",
  "InstrumentID": "159736",
  "InstrumentName": "食品饮料ETF天弘",
  "ProductID": "",
  "ProductName": "",
  "ProductType": null,
  "ExchangeCode": "159736",
  "UniCode": "159736",
  "CreateDate": "0",
  "OpenDate": "20210927",
  "ExpireDate": "99999999",
  "PreClose": 0.712,
  "SettlementPrice": 0.712,
  "UpStopPrice": 0.783,
  "DownStopPrice": 0.641,
  "FloatVolume": 6860394457.0,
  "TotalVolume": 6860394457.0,
  "LongMarginRatio": 0.0,
  "ShortMarginRatio": 0.0,
  "PriceTick": 0.001,
  "VolumeMultiple": 1,
  "MainContract": 0,
  "LastVolume": 0,
  "InstrumentStatus": 0,
  "IsTrading": false,
  "IsRecent": false,
  "ProductTradeQuota": 0,
  "ContractTradeQuota": 0,
  "ProductOpenInterestQuota": 0,
  "ContractOpenInterestQuota": 0
}