{
  "ExchangeID": "SZ",
  "InstrumentID": "159974",
  "InstrumentName": "央企创新ETF",
  "ProductID": "",
  "ProductName": "",
  "ProductType": null,
  "ExchangeCode": "159974",
  "UniCode": "159974",
  "CreateDate": "0",
  "OpenDate": "20191218",
  "ExpireDate": "99999999",
  "PreClose": 1.681,
  "SettlementPrice": 1.681,
  "UpStopPrice": 1.849,
  "DownStopPrice": 1.5130000000000001,
  "FloatVolume": 78432422.0,
  "TotalVolume": 85432422.0,
  "LongMarginRatio": 0.0,
  "ShortMarginRatio": 0.0,
  "PriceTick": 0.001,
  "VolumeMultiple": 1,
  "MainContract": 0,
  "LastVolume": 0,
  "InstrumentStatus": 0,
  "IsTrading": false,
  "IsRecent": false,
  "ProductTradeQuota": 0,
  "ContractTradeQuota": 0,
  "ProductOpenInterestQuota": 0,
  "ContractOpenInterestQuota": 0
}