{
  "ExchangeID": "SZ",
  "InstrumentID": "160223",
  "InstrumentName": "创业板LOF",
  "ProductID": "",
  "ProductName": "",
  "ProductType": null,
  "ExchangeCode": "160223",
  "UniCode": "160223",
  "CreateDate": "0",
  "OpenDate": "20161128",
  "ExpireDate": "99999999",
  "PreClose": 1.307,
  "SettlementPrice": 1.307,
  "UpStopPrice": 1.568,
  "DownStopPrice": 1.046,
  "FloatVolume": 20782111.0,
  "TotalVolume": 185597292.0,
  "LongMarginRatio": 0.0,
  "ShortMarginRatio": 0.0,
  "PriceTick": 0.001,
  "VolumeMultiple": 1,
  "MainContract": 0,
  "LastVolume": 0,
  "InstrumentStatus": 0,
  "IsTrading": false,
  "IsRecent": false,
  "ProductTradeQuota": 0,
  "ContractTradeQuota": 0,
  "ProductOpenInterestQuota": 0,
  "ContractOpenInterestQuota": 0
}