{
  "ExchangeID": "SZ",
  "InstrumentID": "161118",
  "InstrumentName": "中小企业100LOF",
  "ProductID": "",
  "ProductName": "",
  "ProductType": null,
  "ExchangeCode": "161118",
  "UniCode": "161118",
  "CreateDate": "0",
  "OpenDate": "20191009",
  "ExpireDate": "99999999",
  "PreClose": 1.246,
  "SettlementPrice": 1.246,
  "UpStopPrice": 1.371,
  "DownStopPrice": 1.121,
  "FloatVolume": 28779213.0,
  "TotalVolume": 126447655.0,
  "LongMarginRatio": 0.0,
  "ShortMarginRatio": 0.0,
  "PriceTick": 0.001,
  "VolumeMultiple": 1,
  "MainContract": 0,
  "LastVolume": 0,
  "InstrumentStatus": 0,
  "IsTrading": false,
  "IsRecent": false,
  "ProductTradeQuota": 0,
  "ContractTradeQuota": 0,
  "ProductOpenInterestQuota": 0,
  "ContractOpenInterestQuota": 0
}