{
  "ExchangeID": "SZ",
  "InstrumentID": "161125",
  "InstrumentName": "标普500LOF",
  "ProductID": "",
  "ProductName": "",
  "ProductType": null,
  "ExchangeCode": "161125",
  "UniCode": "161125",
  "CreateDate": "0",
  "OpenDate": "20161214",
  "ExpireDate": "99999999",
  "PreClose": 2.759,
  "SettlementPrice": 2.759,
  "UpStopPrice": 3.035,
  "DownStopPrice": 2.483,
  "FloatVolume": 168441122.0,
  "TotalVolume": 353928416.0,
  "LongMarginRatio": 0.0,
  "ShortMarginRatio": 0.0,
  "PriceTick": 0.001,
  "VolumeMultiple": 1,
  "MainContract": 0,
  "LastVolume": 0,
  "InstrumentStatus": 0,
  "IsTrading": false,
  "IsRecent": false,
  "ProductTradeQuota": 0,
  "ContractTradeQuota": 0,
  "ProductOpenInterestQuota": 0,
  "ContractOpenInterestQuota": 0
}