{
  "ExchangeID": "SZ",
  "InstrumentID": "164105",
  "InstrumentName": "华富强债LOF",
  "ProductID": "",
  "ProductName": "",
  "ProductType": null,
  "ExchangeCode": "164105",
  "UniCode": "164105",
  "CreateDate": "0",
  "OpenDate": "20101011",
  "ExpireDate": "99999999",
  "PreClose": 1.662,
  "SettlementPrice": 1.662,
  "UpStopPrice": 1.828,
  "DownStopPrice": 1.496,
  "FloatVolume": 5567768.0,
  "TotalVolume": 543425705.0,
  "LongMarginRatio": 0.0,
  "ShortMarginRatio": 0.0,
  "PriceTick": 0.001,
  "VolumeMultiple": 1,
  "MainContract": 0,
  "LastVolume": 0,
  "InstrumentStatus": 0,
  "IsTrading": false,
  "IsRecent": false,
  "ProductTradeQuota": 0,
  "ContractTradeQuota": 0,
  "ProductOpenInterestQuota": 0,
  "ContractOpenInterestQuota": 0
}