{
  "ExchangeID": "SZ",
  "InstrumentID": "300244",
  "InstrumentName": "迪安诊断",
  "ProductID": "",
  "ProductName": "",
  "ProductType": null,
  "ExchangeCode": "300244",
  "UniCode": "300244",
  "CreateDate": "0",
  "OpenDate": "20110719",
  "ExpireDate": "99999999",
  "PreClose": 16.04,
  "SettlementPrice": 16.04,
  "UpStopPrice": 19.25,
  "DownStopPrice": 12.83,
  "FloatVolume": 501459061.0,
  "TotalVolume": 624979436.0,
  "LongMarginRatio": 0.0,
  "ShortMarginRatio": 0.0,
  "PriceTick": 0.01,
  "VolumeMultiple": 1,
  "MainContract": 0,
  "LastVolume": 0,
  "InstrumentStatus": 0,
  "IsTrading": false,
  "IsRecent": false,
  "ProductTradeQuota": 0,
  "ContractTradeQuota": 0,
  "ProductOpenInterestQuota": 0,
  "ContractOpenInterestQuota": 0
}