{
  "ExchangeID": "SZ",
  "InstrumentID": "300527",
  "InstrumentName": "中船应急",
  "ProductID": "",
  "ProductName": "",
  "ProductType": null,
  "ExchangeCode": "300527",
  "UniCode": "300527",
  "CreateDate": "0",
  "OpenDate": "20160805",
  "ExpireDate": "99999999",
  "PreClose": 11.31,
  "SettlementPrice": 11.31,
  "UpStopPrice": 13.57,
  "DownStopPrice": 9.05,
  "FloatVolume": 986902597.0,
  "TotalVolume": 986902597.0,
  "LongMarginRatio": 0.0,
  "ShortMarginRatio": 0.0,
  "PriceTick": 0.01,
  "VolumeMultiple": 1,
  "MainContract": 0,
  "LastVolume": 0,
  "InstrumentStatus": 0,
  "IsTrading": false,
  "IsRecent": false,
  "ProductTradeQuota": 0,
  "ContractTradeQuota": 0,
  "ProductOpenInterestQuota": 0,
  "ContractOpenInterestQuota": 0
}