{
  "ExchangeID": "SZ",
  "InstrumentID": "300612",
  "InstrumentName": "宣亚国际",
  "ProductID": "",
  "ProductName": "",
  "ProductType": null,
  "ExchangeCode": "300612",
  "UniCode": "300612",
  "CreateDate": "0",
  "OpenDate": "20170215",
  "ExpireDate": "99999999",
  "PreClose": 15.74,
  "SettlementPrice": 15.74,
  "UpStopPrice": 18.89,
  "DownStopPrice": 12.59,
  "FloatVolume": 179879496.0,
  "TotalVolume": 180454496.0,
  "LongMarginRatio": 0.0,
  "ShortMarginRatio": 0.0,
  "PriceTick": 0.01,
  "VolumeMultiple": 1,
  "MainContract": 0,
  "LastVolume": 0,
  "InstrumentStatus": 0,
  "IsTrading": false,
  "IsRecent": false,
  "ProductTradeQuota": 0,
  "ContractTradeQuota": 0,
  "ProductOpenInterestQuota": 0,
  "ContractOpenInterestQuota": 0
}