{
  "ExchangeID": "SZ",
  "InstrumentID": "300665",
  "InstrumentName": "飞鹿股份",
  "ProductID": "",
  "ProductName": "",
  "ProductType": null,
  "ExchangeCode": "300665",
  "UniCode": "300665",
  "CreateDate": "0",
  "OpenDate": "20170613",
  "ExpireDate": "99999999",
  "PreClose": 9.54,
  "SettlementPrice": 9.54,
  "UpStopPrice": 11.450000000000001,
  "DownStopPrice": 7.63,
  "FloatVolume": 150528635.0,
  "TotalVolume": 199862378.0,
  "LongMarginRatio": 0.0,
  "ShortMarginRatio": 0.0,
  "PriceTick": 0.01,
  "VolumeMultiple": 1,
  "MainContract": 0,
  "LastVolume": 0,
  "InstrumentStatus": 0,
  "IsTrading": false,
  "IsRecent": false,
  "ProductTradeQuota": 0,
  "ContractTradeQuota": 0,
  "ProductOpenInterestQuota": 0,
  "ContractOpenInterestQuota": 0
}