{
  "ExchangeID": "SZ",
  "InstrumentID": "300745",
  "InstrumentName": "欣锐科技",
  "ProductID": "",
  "ProductName": "",
  "ProductType": null,
  "ExchangeCode": "300745",
  "UniCode": "300745",
  "CreateDate": "0",
  "OpenDate": "20180523",
  "ExpireDate": "99999999",
  "PreClose": 19.83,
  "SettlementPrice": 19.83,
  "UpStopPrice": 23.8,
  "DownStopPrice": 15.860000000000001,
  "FloatVolume": 141285215.0,
  "TotalVolume": 167614391.0,
  "LongMarginRatio": 0.0,
  "ShortMarginRatio": 0.0,
  "PriceTick": 0.01,
  "VolumeMultiple": 1,
  "MainContract": 0,
  "LastVolume": 0,
  "InstrumentStatus": 0,
  "IsTrading": false,
  "IsRecent": false,
  "ProductTradeQuota": 0,
  "ContractTradeQuota": 0,
  "ProductOpenInterestQuota": 0,
  "ContractOpenInterestQuota": 0
}