{
  "ExchangeID": "SZ",
  "InstrumentID": "300811",
  "InstrumentName": "铂科新材",
  "ProductID": "",
  "ProductName": "",
  "ProductType": null,
  "ExchangeCode": "300811",
  "UniCode": "300811",
  "CreateDate": "0",
  "OpenDate": "20191230",
  "ExpireDate": "99999999",
  "PreClose": 57.26,
  "SettlementPrice": 57.26,
  "UpStopPrice": 68.71000000000001,
  "DownStopPrice": 45.81,
  "FloatVolume": 230340837.0,
  "TotalVolume": 289234574.0,
  "LongMarginRatio": 0.0,
  "ShortMarginRatio": 0.0,
  "PriceTick": 0.01,
  "VolumeMultiple": 1,
  "MainContract": 0,
  "LastVolume": 0,
  "InstrumentStatus": 0,
  "IsTrading": false,
  "IsRecent": false,
  "ProductTradeQuota": 0,
  "ContractTradeQuota": 0,
  "ProductOpenInterestQuota": 0,
  "ContractOpenInterestQuota": 0
}