{
  "ExchangeID": "SZ",
  "InstrumentID": "300900",
  "InstrumentName": "广联航空",
  "ProductID": "",
  "ProductName": "",
  "ProductType": null,
  "ExchangeCode": "300900",
  "UniCode": "300900",
  "CreateDate": "0",
  "OpenDate": "20201029",
  "ExpireDate": "99999999",
  "PreClose": 21.01,
  "SettlementPrice": 21.01,
  "UpStopPrice": 25.21,
  "DownStopPrice": 16.81,
  "FloatVolume": 220288241.0,
  "TotalVolume": 297149916.0,
  "LongMarginRatio": 0.0,
  "ShortMarginRatio": 0.0,
  "PriceTick": 0.01,
  "VolumeMultiple": 1,
  "MainContract": 0,
  "LastVolume": 0,
  "InstrumentStatus": 0,
  "IsTrading": false,
  "IsRecent": false,
  "ProductTradeQuota": 0,
  "ContractTradeQuota": 0,
  "ProductOpenInterestQuota": 0,
  "ContractOpenInterestQuota": 0
}