{
  "ExchangeID": "SZ",
  "InstrumentID": "300987",
  "InstrumentName": "川网传媒",
  "ProductID": "",
  "ProductName": "",
  "ProductType": null,
  "ExchangeCode": "300987",
  "UniCode": "300987",
  "CreateDate": "0",
  "OpenDate": "20210511",
  "ExpireDate": "99999999",
  "PreClose": 20.06,
  "SettlementPrice": 20.06,
  "UpStopPrice": 24.07,
  "DownStopPrice": 16.05,
  "FloatVolume": 173368000.0,
  "TotalVolume": 173368000.0,
  "LongMarginRatio": 0.0,
  "ShortMarginRatio": 0.0,
  "PriceTick": 0.01,
  "VolumeMultiple": 1,
  "MainContract": 0,
  "LastVolume": 0,
  "InstrumentStatus": 0,
  "IsTrading": false,
  "IsRecent": false,
  "ProductTradeQuota": 0,
  "ContractTradeQuota": 0,
  "ProductOpenInterestQuota": 0,
  "ContractOpenInterestQuota": 0
}