{
  "ExchangeID": "SH",
  "InstrumentID": "501008",
  "InstrumentName": "互联网医疗LOFC",
  "ProductID": "",
  "ProductName": "",
  "ProductType": null,
  "ExchangeCode": "501008",
  "UniCode": "501008",
  "CreateDate": "0",
  "OpenDate": "20170220",
  "ExpireDate": "99999999",
  "PreClose": 0.975,
  "SettlementPrice": 0.975,
  "UpStopPrice": 1.073,
  "DownStopPrice": 0.878,
  "FloatVolume": 202746267.0,
  "TotalVolume": 202746267.0,
  "LongMarginRatio": 0.0,
  "ShortMarginRatio": 0.0,
  "PriceTick": 0.001,
  "VolumeMultiple": 1,
  "MainContract": 0,
  "LastVolume": 0,
  "InstrumentStatus": 0,
  "IsTrading": false,
  "IsRecent": false,
  "ProductTradeQuota": 0,
  "ContractTradeQuota": 0,
  "ProductOpenInterestQuota": 0,
  "ContractOpenInterestQuota": 0
}