{
  "ExchangeID": "SH",
  "InstrumentID": "501218",
  "InstrumentName": "工银睿智进取FOF",
  "ProductID": "",
  "ProductName": "",
  "ProductType": null,
  "ExchangeCode": "501218",
  "UniCode": "501218",
  "CreateDate": "0",
  "OpenDate": "20211217",
  "ExpireDate": "99999999",
  "PreClose": 0.942,
  "SettlementPrice": 0.942,
  "UpStopPrice": 1.036,
  "DownStopPrice": 0.848,
  "FloatVolume": 172585190.0,
  "TotalVolume": 172585190.0,
  "LongMarginRatio": 0.0,
  "ShortMarginRatio": 0.0,
  "PriceTick": 0.001,
  "VolumeMultiple": 1,
  "MainContract": 0,
  "LastVolume": 0,
  "InstrumentStatus": 0,
  "IsTrading": false,
  "IsRecent": false,
  "ProductTradeQuota": 0,
  "ContractTradeQuota": 0,
  "ProductOpenInterestQuota": 0,
  "ContractOpenInterestQuota": 0
}