{
  "ExchangeID": "SH",
  "InstrumentID": "508096",
  "InstrumentName": "中航京能光伏REIT",
  "ProductID": "",
  "ProductName": "",
  "ProductType": null,
  "ExchangeCode": "508096",
  "UniCode": "508096",
  "CreateDate": "0",
  "OpenDate": "20230329",
  "ExpireDate": "99999999",
  "PreClose": 11.715,
  "SettlementPrice": 11.715,
  "UpStopPrice": 12.887,
  "DownStopPrice": 10.544,
  "FloatVolume": 0.0,
  "TotalVolume": 0.0,
  "LongMarginRatio": 0.0,
  "ShortMarginRatio": 0.0,
  "PriceTick": 0.001,
  "VolumeMultiple": 1,
  "MainContract": 0,
  "LastVolume": 0,
  "InstrumentStatus": 0,
  "IsTrading": false,
  "IsRecent": false,
  "ProductTradeQuota": 0,
  "ContractTradeQuota": 0,
  "ProductOpenInterestQuota": 0,
  "ContractOpenInterestQuota": 0
}