{
  "ExchangeID": "SH",
  "InstrumentID": "512670",
  "InstrumentName": "国防ETF",
  "ProductID": "",
  "ProductName": "",
  "ProductType": null,
  "ExchangeCode": "512670",
  "UniCode": "512670",
  "CreateDate": "0",
  "OpenDate": "20190801",
  "ExpireDate": "99999999",
  "PreClose": 0.817,
  "SettlementPrice": 0.817,
  "UpStopPrice": 0.899,
  "DownStopPrice": 0.735,
  "FloatVolume": 7297652628.0,
  "TotalVolume": 7297652628.0,
  "LongMarginRatio": 0.0,
  "ShortMarginRatio": 0.0,
  "PriceTick": 0.001,
  "VolumeMultiple": 1,
  "MainContract": 0,
  "LastVolume": 0,
  "InstrumentStatus": 0,
  "IsTrading": false,
  "IsRecent": false,
  "ProductTradeQuota": 0,
  "ContractTradeQuota": 0,
  "ProductOpenInterestQuota": 0,
  "ContractOpenInterestQuota": 0
}