{
  "ExchangeID": "SH",
  "InstrumentID": "588990",
  "InstrumentName": "科创芯片ETF博时",
  "ProductID": "",
  "ProductName": "",
  "ProductType": null,
  "ExchangeCode": "588990",
  "UniCode": "588990",
  "CreateDate": "0",
  "OpenDate": "20240816",
  "ExpireDate": "99999999",
  "PreClose": 1.691,
  "SettlementPrice": 1.691,
  "UpStopPrice": 2.029,
  "DownStopPrice": 1.353,
  "FloatVolume": 143745420.0,
  "TotalVolume": 143745420.0,
  "LongMarginRatio": 0.0,
  "ShortMarginRatio": 0.0,
  "PriceTick": 0.001,
  "VolumeMultiple": 1,
  "MainContract": 0,
  "LastVolume": 0,
  "InstrumentStatus": 0,
  "IsTrading": false,
  "IsRecent": false,
  "ProductTradeQuota": 0,
  "ContractTradeQuota": 0,
  "ProductOpenInterestQuota": 0,
  "ContractOpenInterestQuota": 0
}