{
  "ExchangeID": "SH",
  "InstrumentID": "600022",
  "InstrumentName": "山东钢铁",
  "ProductID": "",
  "ProductName": "",
  "ProductType": null,
  "ExchangeCode": "600022",
  "UniCode": "600022",
  "CreateDate": "0",
  "OpenDate": "20040629",
  "ExpireDate": "99999999",
  "PreClose": 1.55,
  "SettlementPrice": 1.55,
  "UpStopPrice": 1.71,
  "DownStopPrice": 1.4,
  "FloatVolume": 10698849554.0,
  "TotalVolume": 10698849554.0,
  "LongMarginRatio": 0.0,
  "ShortMarginRatio": 0.0,
  "PriceTick": 0.01,
  "VolumeMultiple": 1,
  "MainContract": 0,
  "LastVolume": 0,
  "InstrumentStatus": 0,
  "IsTrading": false,
  "IsRecent": false,
  "ProductTradeQuota": 0,
  "ContractTradeQuota": 0,
  "ProductOpenInterestQuota": 0,
  "ContractOpenInterestQuota": 0
}