{
  "ExchangeID": "SH",
  "InstrumentID": "600136",
  "InstrumentName": "ST明诚",
  "ProductID": "",
  "ProductName": "",
  "ProductType": null,
  "ExchangeCode": "600136",
  "UniCode": "600136",
  "CreateDate": "0",
  "OpenDate": "19980303",
  "ExpireDate": "99999999",
  "PreClose": 1.97,
  "SettlementPrice": 1.97,
  "UpStopPrice": 2.07,
  "DownStopPrice": 1.87,
  "FloatVolume": 1943089494.0,
  "TotalVolume": 2040825931.0,
  "LongMarginRatio": 0.0,
  "ShortMarginRatio": 0.0,
  "PriceTick": 0.01,
  "VolumeMultiple": 1,
  "MainContract": 0,
  "LastVolume": 0,
  "InstrumentStatus": 0,
  "IsTrading": false,
  "IsRecent": false,
  "ProductTradeQuota": 0,
  "ContractTradeQuota": 0,
  "ProductOpenInterestQuota": 0,
  "ContractOpenInterestQuota": 0
}