{
  "ExchangeID": "SH",
  "InstrumentID": "600160",
  "InstrumentName": "巨化股份",
  "ProductID": "",
  "ProductName": "",
  "ProductType": null,
  "ExchangeCode": "600160",
  "UniCode": "600160",
  "CreateDate": "0",
  "OpenDate": "19980626",
  "ExpireDate": "99999999",
  "PreClose": 26.92,
  "SettlementPrice": 26.92,
  "UpStopPrice": 29.61,
  "DownStopPrice": 24.23,
  "FloatVolume": 2699746081.0,
  "TotalVolume": 2699746081.0,
  "LongMarginRatio": 0.0,
  "ShortMarginRatio": 0.0,
  "PriceTick": 0.01,
  "VolumeMultiple": 1,
  "MainContract": 0,
  "LastVolume": 0,
  "InstrumentStatus": 0,
  "IsTrading": false,
  "IsRecent": false,
  "ProductTradeQuota": 0,
  "ContractTradeQuota": 0,
  "ProductOpenInterestQuota": 0,
  "ContractOpenInterestQuota": 0
}