{
  "ExchangeID": "SH",
  "InstrumentID": "600233",
  "InstrumentName": "圆通速递",
  "ProductID": "",
  "ProductName": "",
  "ProductType": null,
  "ExchangeCode": "600233",
  "UniCode": "600233",
  "CreateDate": "0",
  "OpenDate": "20000608",
  "ExpireDate": "99999999",
  "PreClose": 15.29,
  "SettlementPrice": 15.29,
  "UpStopPrice": 16.82,
  "DownStopPrice": 13.76,
  "FloatVolume": 3420226138.0,
  "TotalVolume": 3420226138.0,
  "LongMarginRatio": 0.0,
  "ShortMarginRatio": 0.0,
  "PriceTick": 0.01,
  "VolumeMultiple": 1,
  "MainContract": 0,
  "LastVolume": 0,
  "InstrumentStatus": 0,
  "IsTrading": false,
  "IsRecent": false,
  "ProductTradeQuota": 0,
  "ContractTradeQuota": 0,
  "ProductOpenInterestQuota": 0,
  "ContractOpenInterestQuota": 0
}