{
  "ExchangeID": "SH",
  "InstrumentID": "600876",
  "InstrumentName": "凯盛新能",
  "ProductID": "",
  "ProductName": "",
  "ProductType": null,
  "ExchangeCode": "600876",
  "UniCode": "600876",
  "CreateDate": "0",
  "OpenDate": "19951031",
  "ExpireDate": "99999999",
  "PreClose": 11.36,
  "SettlementPrice": 11.36,
  "UpStopPrice": 12.5,
  "DownStopPrice": 10.22,
  "FloatVolume": 395674963.0,
  "TotalVolume": 395674963.0,
  "LongMarginRatio": 0.0,
  "ShortMarginRatio": 0.0,
  "PriceTick": 0.01,
  "VolumeMultiple": 1,
  "MainContract": 0,
  "LastVolume": 0,
  "InstrumentStatus": 0,
  "IsTrading": false,
  "IsRecent": false,
  "ProductTradeQuota": 0,
  "ContractTradeQuota": 0,
  "ProductOpenInterestQuota": 0,
  "ContractOpenInterestQuota": 0
}