{
  "ExchangeID": "SH",
  "InstrumentID": "600875",
  "InstrumentName": "东方电气",
  "ProductID": "",
  "ProductName": "",
  "ProductType": null,
  "ExchangeCode": "600875",
  "UniCode": "600875",
  "CreateDate": "0",
  "OpenDate": "19951010",
  "ExpireDate": "99999999",
  "PreClose": 20.93,
  "SettlementPrice": 20.93,
  "UpStopPrice": 23.02,
  "DownStopPrice": 18.84,
  "FloatVolume": 2023579060.0,
  "TotalVolume": 3050360326.0,
  "LongMarginRatio": 0.0,
  "ShortMarginRatio": 0.0,
  "PriceTick": 0.01,
  "VolumeMultiple": 1,
  "MainContract": 0,
  "LastVolume": 0,
  "InstrumentStatus": 0,
  "IsTrading": false,
  "IsRecent": false,
  "ProductTradeQuota": 0,
  "ContractTradeQuota": 0,
  "ProductOpenInterestQuota": 0,
  "ContractOpenInterestQuota": 0
}