{
  "ExchangeID": "SH",
  "InstrumentID": "601006",
  "InstrumentName": "大秦铁路",
  "ProductID": "",
  "ProductName": "",
  "ProductType": null,
  "ExchangeCode": "601006",
  "UniCode": "601006",
  "CreateDate": "0",
  "OpenDate": "20060801",
  "ExpireDate": "99999999",
  "PreClose": 6.73,
  "SettlementPrice": 6.73,
  "UpStopPrice": 7.4,
  "DownStopPrice": 6.06,
  "FloatVolume": 20147177716.0,
  "TotalVolume": 20147177716.0,
  "LongMarginRatio": 0.0,
  "ShortMarginRatio": 0.0,
  "PriceTick": 0.01,
  "VolumeMultiple": 1,
  "MainContract": 0,
  "LastVolume": 0,
  "InstrumentStatus": 0,
  "IsTrading": false,
  "IsRecent": false,
  "ProductTradeQuota": 0,
  "ContractTradeQuota": 0,
  "ProductOpenInterestQuota": 0,
  "ContractOpenInterestQuota": 0
}