{
  "ExchangeID": "SH",
  "InstrumentID": "603009",
  "InstrumentName": "北特科技",
  "ProductID": "",
  "ProductName": "",
  "ProductType": null,
  "ExchangeCode": "603009",
  "UniCode": "603009",
  "CreateDate": "0",
  "OpenDate": "20140718",
  "ExpireDate": "99999999",
  "PreClose": 40.56,
  "SettlementPrice": 40.56,
  "UpStopPrice": 44.62,
  "DownStopPrice": 36.5,
  "FloatVolume": 338408970.0,
  "TotalVolume": 338526168.0,
  "LongMarginRatio": 0.0,
  "ShortMarginRatio": 0.0,
  "PriceTick": 0.01,
  "VolumeMultiple": 1,
  "MainContract": 0,
  "LastVolume": 0,
  "InstrumentStatus": 0,
  "IsTrading": false,
  "IsRecent": false,
  "ProductTradeQuota": 0,
  "ContractTradeQuota": 0,
  "ProductOpenInterestQuota": 0,
  "ContractOpenInterestQuota": 0
}