{
  "ExchangeID": "SH",
  "InstrumentID": "603055",
  "InstrumentName": "台华新材",
  "ProductID": "",
  "ProductName": "",
  "ProductType": null,
  "ExchangeCode": "603055",
  "UniCode": "603055",
  "CreateDate": "0",
  "OpenDate": "20170921",
  "ExpireDate": "99999999",
  "PreClose": 10.23,
  "SettlementPrice": 10.23,
  "UpStopPrice": 11.25,
  "DownStopPrice": 9.21,
  "FloatVolume": 885452633.0,
  "TotalVolume": 890292633.0,
  "LongMarginRatio": 0.0,
  "ShortMarginRatio": 0.0,
  "PriceTick": 0.01,
  "VolumeMultiple": 1,
  "MainContract": 0,
  "LastVolume": 0,
  "InstrumentStatus": 0,
  "IsTrading": false,
  "IsRecent": false,
  "ProductTradeQuota": 0,
  "ContractTradeQuota": 0,
  "ProductOpenInterestQuota": 0,
  "ContractOpenInterestQuota": 0
}