{
  "ExchangeID": "SH",
  "InstrumentID": "603150",
  "InstrumentName": "万朗磁塑",
  "ProductID": "",
  "ProductName": "",
  "ProductType": null,
  "ExchangeCode": "603150",
  "UniCode": "603150",
  "CreateDate": "0",
  "OpenDate": "20220124",
  "ExpireDate": "99999999",
  "PreClose": 33.48,
  "SettlementPrice": 33.48,
  "UpStopPrice": 36.83,
  "DownStopPrice": 30.13,
  "FloatVolume": 85483000.0,
  "TotalVolume": 85483000.0,
  "LongMarginRatio": 0.0,
  "ShortMarginRatio": 0.0,
  "PriceTick": 0.01,
  "VolumeMultiple": 1,
  "MainContract": 0,
  "LastVolume": 0,
  "InstrumentStatus": 0,
  "IsTrading": false,
  "IsRecent": false,
  "ProductTradeQuota": 0,
  "ContractTradeQuota": 0,
  "ProductOpenInterestQuota": 0,
  "ContractOpenInterestQuota": 0
}