{
  "ExchangeID": "SH",
  "InstrumentID": "603335",
  "InstrumentName": "迪生力",
  "ProductID": "",
  "ProductName": "",
  "ProductType": null,
  "ExchangeCode": "603335",
  "UniCode": "603335",
  "CreateDate": "0",
  "OpenDate": "20170620",
  "ExpireDate": "99999999",
  "PreClose": 5.26,
  "SettlementPrice": 5.26,
  "UpStopPrice": 5.79,
  "DownStopPrice": 4.73,
  "FloatVolume": 428144600.0,
  "TotalVolume": 428144600.0,
  "LongMarginRatio": 0.0,
  "ShortMarginRatio": 0.0,
  "PriceTick": 0.01,
  "VolumeMultiple": 1,
  "MainContract": 0,
  "LastVolume": 0,
  "InstrumentStatus": 0,
  "IsTrading": false,
  "IsRecent": false,
  "ProductTradeQuota": 0,
  "ContractTradeQuota": 0,
  "ProductOpenInterestQuota": 0,
  "ContractOpenInterestQuota": 0
}