{
  "ExchangeID": "SH",
  "InstrumentID": "603663",
  "InstrumentName": "三祥新材",
  "ProductID": "",
  "ProductName": "",
  "ProductType": null,
  "ExchangeCode": "603663",
  "UniCode": "603663",
  "CreateDate": "0",
  "OpenDate": "20160801",
  "ExpireDate": "99999999",
  "PreClose": 28.03,
  "SettlementPrice": 28.03,
  "UpStopPrice": 30.83,
  "DownStopPrice": 25.23,
  "FloatVolume": 422819750.0,
  "TotalVolume": 423299750.0,
  "LongMarginRatio": 0.0,
  "ShortMarginRatio": 0.0,
  "PriceTick": 0.01,
  "VolumeMultiple": 1,
  "MainContract": 0,
  "LastVolume": 0,
  "InstrumentStatus": 0,
  "IsTrading": false,
  "IsRecent": false,
  "ProductTradeQuota": 0,
  "ContractTradeQuota": 0,
  "ProductOpenInterestQuota": 0,
  "ContractOpenInterestQuota": 0
}