{
  "ExchangeID": "SH",
  "InstrumentID": "605588",
  "InstrumentName": "冠石科技",
  "ProductID": "",
  "ProductName": "",
  "ProductType": null,
  "ExchangeCode": "605588",
  "UniCode": "605588",
  "CreateDate": "0",
  "OpenDate": "20210812",
  "ExpireDate": "10000991",
  "PreClose": 47.55,
  "SettlementPrice": 47.55,
  "UpStopPrice": 52.31,
  "DownStopPrice": 42.8,
  "FloatVolume": 73099561.0,
  "TotalVolume": 73468201.0,
  "LongMarginRatio": 0.0,
  "ShortMarginRatio": 0.0,
  "PriceTick": 0.01,
  "VolumeMultiple": 1,
  "MainContract": 0,
  "LastVolume": 0,
  "InstrumentStatus": 0,
  "IsTrading": false,
  "IsRecent": false,
  "ProductTradeQuota": 0,
  "ContractTradeQuota": 0,
  "ProductOpenInterestQuota": 0,
  "ContractOpenInterestQuota": 0
}