{
  "ExchangeID": "SH",
  "InstrumentID": "688105",
  "InstrumentName": "诺唯赞",
  "ProductID": "",
  "ProductName": "",
  "ProductType": null,
  "ExchangeCode": "688105",
  "UniCode": "688105",
  "CreateDate": "0",
  "OpenDate": "20211115",
  "ExpireDate": "10011011",
  "PreClose": 25.03,
  "SettlementPrice": 25.03,
  "UpStopPrice": 30.04,
  "DownStopPrice": 20.02,
  "FloatVolume": 397734544.0,
  "TotalVolume": 397734544.0,
  "LongMarginRatio": 0.0,
  "ShortMarginRatio": 0.0,
  "PriceTick": 0.01,
  "VolumeMultiple": 1,
  "MainContract": 0,
  "LastVolume": 0,
  "InstrumentStatus": 0,
  "IsTrading": false,
  "IsRecent": false,
  "ProductTradeQuota": 0,
  "ContractTradeQuota": 0,
  "ProductOpenInterestQuota": 0,
  "ContractOpenInterestQuota": 0
}