{
  "ExchangeID": "SH",
  "InstrumentID": "688280",
  "InstrumentName": "精进电动-UW",
  "ProductID": "",
  "ProductName": "",
  "ProductType": null,
  "ExchangeCode": "688280",
  "UniCode": "688280",
  "CreateDate": "0",
  "OpenDate": "20211027",
  "ExpireDate": "10001111",
  "PreClose": 7.5,
  "SettlementPrice": 7.5,
  "UpStopPrice": 9.0,
  "DownStopPrice": 6.0,
  "FloatVolume": 520544145.0,
  "TotalVolume": 590221667.0,
  "LongMarginRatio": 0.0,
  "ShortMarginRatio": 0.0,
  "PriceTick": 0.01,
  "VolumeMultiple": 1,
  "MainContract": 0,
  "LastVolume": 0,
  "InstrumentStatus": 0,
  "IsTrading": false,
  "IsRecent": false,
  "ProductTradeQuota": 0,
  "ContractTradeQuota": 0,
  "ProductOpenInterestQuota": 0,
  "ContractOpenInterestQuota": 0
}