{
  "ExchangeID": "SH",
  "InstrumentID": "688205",
  "InstrumentName": "德科立",
  "ProductID": "",
  "ProductName": "",
  "ProductType": null,
  "ExchangeCode": "688205",
  "UniCode": "688205",
  "CreateDate": "0",
  "OpenDate": "20220809",
  "ExpireDate": "10011011",
  "PreClose": 55.29,
  "SettlementPrice": 55.29,
  "UpStopPrice": 66.35,
  "DownStopPrice": 44.23,
  "FloatVolume": 89335887.0,
  "TotalVolume": 158285329.0,
  "LongMarginRatio": 0.0,
  "ShortMarginRatio": 0.0,
  "PriceTick": 0.01,
  "VolumeMultiple": 1,
  "MainContract": 0,
  "LastVolume": 0,
  "InstrumentStatus": 0,
  "IsTrading": false,
  "IsRecent": false,
  "ProductTradeQuota": 0,
  "ContractTradeQuota": 0,
  "ProductOpenInterestQuota": 0,
  "ContractOpenInterestQuota": 0
}