{
  "ExchangeID": "SH",
  "InstrumentID": "688458",
  "InstrumentName": "美芯晟",
  "ProductID": "",
  "ProductName": "",
  "ProductType": null,
  "ExchangeCode": "688458",
  "UniCode": "688458",
  "CreateDate": "0",
  "OpenDate": "20230522",
  "ExpireDate": "10011011",
  "PreClose": 40.82,
  "SettlementPrice": 40.82,
  "UpStopPrice": 48.98,
  "DownStopPrice": 32.66,
  "FloatVolume": 85068541.0,
  "TotalVolume": 111536629.0,
  "LongMarginRatio": 0.0,
  "ShortMarginRatio": 0.0,
  "PriceTick": 0.01,
  "VolumeMultiple": 1,
  "MainContract": 0,
  "LastVolume": 0,
  "InstrumentStatus": 0,
  "IsTrading": false,
  "IsRecent": false,
  "ProductTradeQuota": 0,
  "ContractTradeQuota": 0,
  "ProductOpenInterestQuota": 0,
  "ContractOpenInterestQuota": 0
}