{
  "ExchangeID": "SH",
  "InstrumentID": "900913",
  "InstrumentName": "国新B股",
  "ProductID": "",
  "ProductName": "",
  "ProductType": null,
  "ExchangeCode": "900913",
  "UniCode": "900913",
  "CreateDate": "0",
  "OpenDate": "19930928",
  "ExpireDate": "99999999",
  "PreClose": 0.236,
  "SettlementPrice": 0.236,
  "UpStopPrice": 0.26,
  "DownStopPrice": 0.212,
  "FloatVolume": 0.0,
  "TotalVolume": 0.0,
  "LongMarginRatio": 0.0,
  "ShortMarginRatio": 0.0,
  "PriceTick": 0.001,
  "VolumeMultiple": 1,
  "MainContract": 0,
  "LastVolume": 0,
  "InstrumentStatus": 0,
  "IsTrading": false,
  "IsRecent": false,
  "ProductTradeQuota": 0,
  "ContractTradeQuota": 0,
  "ProductOpenInterestQuota": 0,
  "ContractOpenInterestQuota": 0
}